ailearn/__init__.py
ailearn/crawler.py
ailearn/ml.py
ailearn/text.py
ailearn/RL/Environment.py
ailearn/RL/TabularRL.py
ailearn/RL/__init__.py
ailearn/Swarm/AFSA.py
ailearn/Swarm/EAS.py
ailearn/Swarm/Evaluation.py
ailearn/Swarm/FA.py
ailearn/Swarm/ModifiedPSO.py
ailearn/Swarm/PSO.py
ailearn/Swarm/__init__.py
ailearn/example/Reinforcement learning.py
ailearn/example/Swarm.py
ailearn/example/__init__.py
ailearn/example/plot_decision_boundary.py
ailearn/nn/__init__.py
ailearn/nn/activations.py
ailearn/nn/losses.py
ailearn/utils/__init__.py
ailearn/utils/distances.py
ailearn/utils/metrics.py
ailearn/utils/torch_utils.py
ailearn/utils/utilities.py
ailearn-0.2.1.12.dist-info/LICENSE
ailearn-0.2.1.12.dist-info/METADATA
ailearn-0.2.1.12.dist-info/WHEEL
ailearn-0.2.1.12.dist-info/top_level.txt
ailearn-0.2.1.12.dist-info/RECORD
